Metadata-Version: 1.1
Name: django-pgcrypto2
Version: 1.4.0
Summary: Python and Django utilities for encrypted fields using pgcrypto.
Home-page: https://github.com/dcwatson/django-pgcrypto
Author: Dan Watson & Fran Lendinez
Author-email: dcwatson@gmail.com
License: BSD
Platform: UNKNOWN
Classifier: Development Status :: 5 - Production/Stable
Classifier: Framework :: Django
Classifier: Intended Audience :: Developers
Classifier: License :: OSI Approved :: BSD License
Classifier: Programming Language :: Python :: 2
Classifier: Programming Language :: Python :: 3
Classifier: Topic :: Database
